odoo/addons/crm_metadata/__init__.py
odoo/addons/crm_metadata/__manifest__.py
odoo/addons/crm_metadata/models/__init__.py
odoo/addons/crm_metadata/models/crm_lead.py
odoo/addons/crm_metadata/models/crm_lead_metadata_line.py
odoo/addons/crm_metadata/security/ir.model.access.csv
odoo/addons/crm_metadata/views/crm_lead.xml
odoo14_addon_crm_metadata-14.0.1.0.0.dist-info/METADATA
odoo14_addon_crm_metadata-14.0.1.0.0.dist-info/WHEEL
odoo14_addon_crm_metadata-14.0.1.0.0.dist-info/top_level.txt
odoo14_addon_crm_metadata-14.0.1.0.0.dist-info/RECORD
