Metadata-Version: 2.1
Name: odoo14-addon-crm-metadata
Version: 14.0.1.0.0
Summary: Add metadata to crm lead
Home-page: UNKNOWN
Author: Coopdevs Treball SCCL
License: UNKNOWN
Platform: UNKNOWN
Classifier: Programming Language :: Python
Classifier: Framework :: Odoo
Classifier: Framework :: Odoo :: 14.0
Requires-Python: >=3.6
Requires-Dist: odoo14-addon-metadata
Requires-Dist: odoo (<14.1dev,>=14.0a)
